MANIFEST.in
README.rst
setup.py
vsummarize/TEMP_MPY_to_videofile_SOUND.mp3
vsummarize/__init__.py
vsummarize/algorithm.py
vsummarize/api.py
vsummarize/rename_to_settings.py
vsummarize/version.py
vsummarize/video.py
vsummarize/youtube.py
vsummarize.egg-info/PKG-INFO
vsummarize.egg-info/SOURCES.txt
vsummarize.egg-info/dependency_links.txt
vsummarize.egg-info/not-zip-safe
vsummarize.egg-info/requires.txt
vsummarize.egg-info/top_level.txt