Metadata-Version: 1.0
Name: vsummarize
Version: 0.0.1
Summary: Python video summarization.
Home-page: https://github.com/codelucas/vsummarize
Author: Lucas Ou-Yang
Author-email: lucasyangpersonal@gmail.com
License: UNKNOWN
Platform: UNKNOWN
